hedra/__init__.py
hedra/_base_client.py
hedra/_client.py
hedra/_compat.py
hedra/_constants.py
hedra/_exceptions.py
hedra/_files.py
hedra/_models.py
hedra/_qs.py
hedra/_resource.py
hedra/_response.py
hedra/_streaming.py
hedra/_types.py
hedra/_version.py
hedra/py.typed
hedra/_utils/__init__.py
hedra/_utils/_logs.py
hedra/_utils/_proxy.py
hedra/_utils/_reflection.py
hedra/_utils/_streams.py
hedra/_utils/_sync.py
hedra/_utils/_transform.py
hedra/_utils/_typing.py
hedra/_utils/_utils.py
hedra/lib/.keep
hedra/resources/__init__.py
hedra/resources/audio.py
hedra/resources/characters.py
hedra/resources/portraits.py
hedra/resources/projects.py
hedra/resources/voices.py
hedra/types/__init__.py
hedra/types/audio_create_params.py
hedra/types/audio_create_response.py
hedra/types/avatar_project_item.py
hedra/types/character_create_params.py
hedra/types/character_create_response.py
hedra/types/portrait_create_params.py
hedra/types/portrait_create_response.py
hedra/types/project_list_response.py
hedra/types/project_sharing_params.py
hedra/types/voice_list_response.py
hedra_python-0.1.2.dist-info/METADATA
hedra_python-0.1.2.dist-info/WHEEL
hedra_python-0.1.2.dist-info/licenses/LICENSE
hedra_python-0.1.2.dist-info/RECORD
